cards/__init__.py
cards/apps.py
cards/base.py
cards/includes.py
cards/standard.py
cards/url_converters.py
cards/card_list/__init__.py
cards/card_list/base.py
cards/card_list/main.py
cards/card_list/tree.py
cards/static/cards/jstree/css/themes/default/32px.png
cards/static/cards/jstree/css/themes/default/40px.png
cards/static/cards/jstree/css/themes/default/style.css
cards/static/cards/jstree/css/themes/default/style.min.css
cards/static/cards/jstree/css/themes/default/throbber.gif
cards/static/cards/jstree/css/themes/default-dark/32px.png
cards/static/cards/jstree/css/themes/default-dark/40px.png
cards/static/cards/jstree/css/themes/default-dark/style.css
cards/static/cards/jstree/css/themes/default-dark/style.min.css
cards/static/cards/jstree/css/themes/default-dark/throbber.gif
cards/static/cards/jstree/css/themes/proton/30px.png
cards/static/cards/jstree/css/themes/proton/32px.png
cards/static/cards/jstree/css/themes/proton/style.css
cards/static/cards/jstree/css/themes/proton/style.min.css
cards/static/cards/jstree/css/themes/proton/throbber.gif
cards/static/cards/jstree/css/themes/proton/fonts/titillium/titilliumweb-bold-webfont.eot
cards/static/cards/jstree/css/themes/proton/fonts/titillium/titilliumweb-bold-webfont.svg
cards/static/cards/jstree/css/themes/proton/fonts/titillium/titilliumweb-bold-webfont.ttf
cards/static/cards/jstree/css/themes/proton/fonts/titillium/titilliumweb-bold-webfont.woff
cards/static/cards/jstree/css/themes/proton/fonts/titillium/titilliumweb-extralight-webfont.eot
cards/static/cards/jstree/css/themes/proton/fonts/titillium/titilliumweb-extralight-webfont.svg
cards/static/cards/jstree/css/themes/proton/fonts/titillium/titilliumweb-extralight-webfont.ttf
cards/static/cards/jstree/css/themes/proton/fonts/titillium/titilliumweb-extralight-webfont.woff
cards/static/cards/jstree/css/themes/proton/fonts/titillium/titilliumweb-regular-webfont.eot
cards/static/cards/jstree/css/themes/proton/fonts/titillium/titilliumweb-regular-webfont.svg
django_cards-0.12.2.dist-info/licenses/LICENSE
django_cards-0.12.2.dist-info/METADATA
django_cards-0.12.2.dist-info/WHEEL
django_cards-0.12.2.dist-info/top_level.txt
django_cards-0.12.2.dist-info/RECORD
