Metadata-Version: 2.4
Name: django-cards
Version: 0.12.2
Summary: Django app that allows you make cards
Home-page: https://github.com/django-advance-utils/django-cards
Author: Thomas Turner
Classifier: Programming Language :: Python :: 3
Classifier: License :: OSI Approved :: MIT License
Classifier: Operating System :: OS Independent
Requires-Python: >=3.6
License-File: LICENSE
Dynamic: author
Dynamic: classifier
Dynamic: description
Dynamic: description-content-type
Dynamic: home-page
Dynamic: license-file
Dynamic: requires-python
Dynamic: summary
